gradio_notebook/__init__.py
gradio_notebook/aiconfig_manager.py
gradio_notebook/events.py
gradio_notebook/gradio_notebook.py
gradio_notebook/gradio_notebook_component.py
gradio_notebook/gradio_notebook_component.pyi
gradio_notebook/session_data.py
gradio_notebook/utils.py
gradio_notebook/templates/component/__vite-browser-external-jWVCDlBL.js
gradio_notebook/templates/component/index.js
gradio_notebook/templates/component/style.css
gradio_notebook/templates/component/wrapper-6f348d45-pgNaiy2L.js
gradio_notebook/templates/example/index.js
gradio_notebook/templates/example/style.css
gradio_gradioworkbook_ap-0.0.25.dist-info/METADATA
gradio_gradioworkbook_ap-0.0.25.dist-info/WHEEL
gradio_gradioworkbook_ap-0.0.25.dist-info/licenses/LICENSE
gradio_gradioworkbook_ap-0.0.25.dist-info/RECORD
